base94/__init__.py
base94/_base94.pyi
base94/_base94.pypy311-pp73-win_amd64.pyd
base94/base72.py
base94/base94.py
base94_rs-0.1.8.dist-info/METADATA
base94_rs-0.1.8.dist-info/WHEEL
base94_rs-0.1.8.dist-info/licenses/LICENSE
base94_rs-0.1.8.dist-info/RECORD
