Metadata-Version: 2.4
Name: base94-rs
Version: 0.1.8
Classifier: Programming Language :: Rust
Classifier: Programming Language :: Python :: Implementation :: CPython
Classifier: Programming Language :: Python :: Implementation :: PyPy
Requires-Dist: pytest ; extra == 'test'
Provides-Extra: test
License-File: LICENSE
Summary: A package allows you to en/decode using base94.
Keywords: Codec,Rust,Base,Base94
Author-email: hibays <hibays@github.com>
Requires-Python: >=3.8
Project-URL: repository, https://github.com/hibays/base94.git
